library/__init__.py
library/runner.py
library/utils.py
library/app/__init__.py
library/app/image_processor.py
library/app/input_manager.py
library/models/__init__.py
library/models/blip_image.py
library/models/cohere.py
library/models/easy_ocr.py
library/testing/__init__.py
library/testing/runner.py
library/testing/tests/__init__.py
library/testing/tests/test_singleton.py
library/testing/tests/test_user_input.py
library/testing/tests/utils_test.py
src/__init__.py
src/utils.py
src/app/__init__.py
src/app/image_processor.py
src/app/input_manager.py
src/models/__init__.py
src/models/blip_image.py
src/models/cohere.py
src/models/easy_ocr.py
src/testing/__init__.py
src/testing/runner.py
src/testing/tests/__init__.py
src/testing/tests/test_singleton.py
src/testing/tests/test_user_input.py
src/testing/tests/utils_test.py
ogicg-1.0.1.dist-info/METADATA
ogicg-1.0.1.dist-info/WHEEL
ogicg-1.0.1.dist-info/top_level.txt
ogicg-1.0.1.dist-info/RECORD
